command_history/__init__.py
command_history/history.py
command_history/tests/__init__.py
command_history/tests/test_command_line.py
command_history/tests/test_history.py
command_history-0.0.0.dist-info/LICENSE
command_history-0.0.0.dist-info/METADATA
command_history-0.0.0.dist-info/WHEEL
command_history-0.0.0.dist-info/top_level.txt
command_history-0.0.0.dist-info/RECORD
