Metadata-Version: 2.1
Name: command-history
Version: 0.0.0
Summary: Get commands history
Home-page: https://github.com/trinhcanhphuc/history.git
Author: Phuc Trinh
Author-email: trinhcanhphuc@gmail.com
License: UNKNOWN
Platform: UNKNOWN
Classifier: Programming Language :: Python :: 3
Classifier: License :: OSI Approved :: MIT License
Classifier: Operating System :: OS Independent
Requires-Python: >=3.6
